{"bricks":{"entity":{"git":{"url":"https://github.com/Q-Agency/QBricks.git","path":"bricks/entity","ref":"29087dff853f2ea16bfd73729037441a6eaf7593"}},"model":{"git":{"url":"https://github.com/Q-Agency/QBricks.git","path":"bricks/model","ref":"29087dff853f2ea16bfd73729037441a6eaf7593"}},"notifier":{"git":{"url":"https://github.com/Q-Agency/QBricks.git","path":"bricks/notifier","ref":"29087dff853f2ea16bfd73729037441a6eaf7593"}},"repository":{"git":{"url":"https://github.com/Q-Agency/QBricks.git","path":"bricks/repository","ref":"29087dff853f2ea16bfd73729037441a6eaf7593"}},"service":{"git":{"url":"https://github.com/Q-Agency/QBricks.git","path":"bricks/service","ref":"29087dff853f2ea16bfd73729037441a6eaf7593"}},"simple_notifier":{"git":{"url":"https://github.com/Q-Agency/QBricks.git","path":"bricks/simple_notifier","ref":"29087dff853f2ea16bfd73729037441a6eaf7593"}}}}